tooner/__init__.py
tooner/invasions.py
tooner/launcher.py
tooner-1.1.1.dist-info/WHEEL
tooner-1.1.1.dist-info/METADATA
tooner-1.1.1.dist-info/RECORD
