Metadata-Version: 2.1
Name: tooner
Version: 1.1.1
Summary: An easier way to manage and launch sessions for Toontown Rewritten.
License: MIT
Author: Jake Brehm
Author-email: mail@jakebrehm.com
Requires-Python: >=3.7,<4.0
Classifier: License :: OSI Approved :: MIT License
Classifier: Programming Language :: Python :: 3
Classifier: Programming Language :: Python :: 3.7
Classifier: Programming Language :: Python :: 3.8
Classifier: Programming Language :: Python :: 3.9
Requires-Dist: requests (>=2.23.0,<3.0.0)
